simple_gpu_queue/__init__.py
simple_gpu_queue/explogger.py
simple_gpu_queue/scripts.py
simple_gpu_queue/simple_gpu_queue.py
simple_gpu_queue-0.1.1.dist-info/LICENSE
simple_gpu_queue-0.1.1.dist-info/METADATA
simple_gpu_queue-0.1.1.dist-info/WHEEL
simple_gpu_queue-0.1.1.dist-info/entry_points.txt
simple_gpu_queue-0.1.1.dist-info/top_level.txt
simple_gpu_queue-0.1.1.dist-info/RECORD
