Metadata-Version: 2.1
Name: simple_gpu_queue
Version: 0.1.1
Summary: Simple GPU Queue: For running lots of smaller experiments on your handful of GPUs, designed for JAX
Home-page: https://github.com/bhoov/simple-gpu-queue
Author: Ben Hoover
Author-email: benhoover34@gmail.com
Classifier: Programming Language :: Python :: 3
Classifier: License :: OSI Approved :: MIT License
Classifier: Operating System :: OS Independent
License-File: LICENSE
Requires-Dist: tyro==0.8.5
Requires-Dist: fastapi[all]==0.112.0
Requires-Dist: gitpython
Requires-Dist: requests==2.32.3
